{
  "noticias_sites": [
    {
      "titulo": "Sítios arqueológicos da Serra do Lajeado (TO) recebem ações de conservação",
      "data": "13/02/2025",
      "resumo": "13/02/2025\n                                        \n                                         - \n                                        Além das medidas já em andamento, está sendo elaborado um Guia Rápido para prevenção de incêndios em sítios arqueológicos",
      "imagem": "https://www.gov.br/iphan/pt-br/assuntos/noticias/sitios-arqueologicos-da-serra-do-lajeado-to-recebem-acoes-de-conservacao/banner-tocantins.jpg/@@images/image",
      "fonte": "www.gov.br/iphan"
    },
    {
      "titulo": "Iphan se reúne com Governo do Amazonas para tratar sobre Igreja de São Sebastião",
      "data": "13/02/2025",
      "resumo": "13/02/2025\n                                        \n                                         - \n                                        A paróquia está interditada desde janeiro, após recomendação do Iphan, para garantir a segurança das pessoas",
      "imagem": "https://www.gov.br/iphan/pt-br/assuntos/noticias/iphan-se-reune-com-governo-do-amazonas-para-tratar-sobre-igreja-de-sao-sebastiao/whatsapp-image-2025-02-12-at-09-04-29-2.jpeg/@@images/image",
      "fonte": "www.gov.br/iphan"
    },
    {
      "titulo": "Iphan monta força-tarefa para atuar no caso da Igreja de São Francisco, em Salvador",
      "data": "12/02/2025",
      "resumo": "12/02/2025\n                                        \n                                         - \n                                        Além de dar suporte à contratação de obras emergenciais na Igreja, equipe ajudará em decisões sobre o Convento e outros imóveis no Centro Histórico da capital baiana.",
      "imagem": "https://www.gov.br/iphan/pt-br/assuntos/noticias/iphan-monta-forca-tarefa-para-atuar-no-caso-da-igreja-de-sao-francisco-em-salvador/bannersite.png/@@images/image",
      "fonte": "www.gov.br/iphan"
    },
    {
      "titulo": "Paes confirma show gratuito de Lady Gaga em Copacabana em maio",
      "data": "Sem data",
      "resumo": "\"Tivemos Madonna no ano passado, esse ano teremos Lady Gaga. Pronto, agora falei\", disse o prefeito em entrevista ao programa PodK",
      "imagem": "https://cdn.brasil247.com/pb-b247gcp/swp/jtjeq9/media/20250213200236_0b7794fd-5971-4bdc-a10f-0fab2147cf6a.webp?w=3840&q=90",
      "fonte": "www.brasil247.com"
    },
    {
      "titulo": "Martinho da Vila: 87 anos de um legado inigualável para a música e a cultura brasileira",
      "data": "Sem data",
      "resumo": "Cantor, compositor, escritor e intelectual do povo, Martinho ultrapassou as barreiras da música para se tornar um verdadeiro símbolo da identidade nacional",
      "imagem": "https://cdn.brasil247.com/pb-b247gcp/swp/jtjeq9/media/20190530150544_06c2b126a96ef9ef85af4ac1d4f4e85dd959ec729056a421c68dc63cd140dd6e.webp?w=3840&q=90",
      "fonte": "www.brasil247.com"
    },
    {
      "titulo": "Editora Thieme está com chamada de trabalho aberta para janeiro",
      "data": "09/01/2025",
      "resumo": "09/01/2025 -\n                Serão aceitos artigos sobre catálise de metais de transição de primeira linha para síntese orgânica",
      "imagem": "https://www.periodicos.capes.gov.br/images/news/Matria_Thieme.png",
      "fonte": "www.periodicos.capes.gov.br"
    },
    {
      "titulo": "Emerald abre chamadas para dezembro de 2024 e janeiro de 2025",
      "data": "30/12/2024",
      "resumo": "30/12/2024 -\n                As produções poderão ser enviadas até 30 e 31 de dezembro, e 15, 16 e 31 de janeiro",
      "imagem": "https://www.periodicos.capes.gov.br/images/Imagem_Matria_Emerald.png",
      "fonte": "www.periodicos.capes.gov.br"
    }
  ],
  "noticias_escritorio": [
    {
      "titulo": "1º Simpósio de Gestão Ambiental do Nordeste e da Caatinga",
      "data": "09/01/2025",
      "resumo": "De 26 a 29 de março, o 1º Simpósio Ambiental Nordeste/Caatinga reúne especialistas que debatem clima, socioeconômia e biodiversidade.",
      "imagem": "https://raw.githubusercontent.com/carlosmargemrio/Noticias/main/imagens/cap.jpg",
      "fonte": "escritoriosaoraimun@iphan.gov.br"
    }
  ]
}